GoBlogZhongwenfanyi/README.md
GoBlogZhongwenfanyi/__init__.py
GoBlogZhongwenfanyi/__main__.py
GoBlogZhongwenfanyi/file.epub
GoBlogZhongwenfanyi/index.html
GoBlogZhongwenfanyi/css/__init__.py
GoBlogZhongwenfanyi/css/annotations.css
GoBlogZhongwenfanyi/css/main.css
GoBlogZhongwenfanyi/css/normalize.css
GoBlogZhongwenfanyi/css/popup.css
GoBlogZhongwenfanyi/font/__init__.py
GoBlogZhongwenfanyi/font/fontello.eot
GoBlogZhongwenfanyi/font/fontello.svg
GoBlogZhongwenfanyi/font/fontello.ttf
GoBlogZhongwenfanyi/font/fontello.woff
GoBlogZhongwenfanyi/img/__init__.py
GoBlogZhongwenfanyi/img/annotator-glyph-sprite.png
GoBlogZhongwenfanyi/img/annotator-icon-sprite.png
GoBlogZhongwenfanyi/img/apple-touch-icon.png
GoBlogZhongwenfanyi/img/cancelfullscreen.png
GoBlogZhongwenfanyi/img/close.png
GoBlogZhongwenfanyi/img/fullscreen.png
GoBlogZhongwenfanyi/img/loader.gif
GoBlogZhongwenfanyi/img/menu-icon.png
GoBlogZhongwenfanyi/img/save.png
GoBlogZhongwenfanyi/img/saved.png
GoBlogZhongwenfanyi/img/settings-s.png
GoBlogZhongwenfanyi/img/settings.png
GoBlogZhongwenfanyi/img/star.png
GoBlogZhongwenfanyi/js/__init__.py
GoBlogZhongwenfanyi/js/epub.js
GoBlogZhongwenfanyi/js/epub.min.js
GoBlogZhongwenfanyi/js/epub.min.map
GoBlogZhongwenfanyi/js/hooks.min.js
GoBlogZhongwenfanyi/js/hooks.min.map
GoBlogZhongwenfanyi/js/reader.js
GoBlogZhongwenfanyi/js/reader.js.map
GoBlogZhongwenfanyi/js/reader.min.js
GoBlogZhongwenfanyi/js/reader.min.map
GoBlogZhongwenfanyi/js/hooks/__init__.py
GoBlogZhongwenfanyi/js/hooks/extensions/__init__.py
GoBlogZhongwenfanyi/js/hooks/extensions/highlight.js
GoBlogZhongwenfanyi/js/libs/__init__.py
GoBlogZhongwenfanyi/js/libs/jquery.min.js
GoBlogZhongwenfanyi/js/libs/localforage.min.js
GoBlogZhongwenfanyi/js/libs/screenfull.js
GoBlogZhongwenfanyi/js/libs/screenfull.min.js
GoBlogZhongwenfanyi/js/libs/zip.min.js
GoBlogZhongwenfanyi/js/plugins/__init__.py
GoBlogZhongwenfanyi/js/plugins/hypothesis.js
GoBlogZhongwenfanyi/js/plugins/search.js
go_blog_zhongwenfanyi-2024.3.6.0.dist-info/METADATA
go_blog_zhongwenfanyi-2024.3.6.0.dist-info/WHEEL
go_blog_zhongwenfanyi-2024.3.6.0.dist-info/entry_points.txt
go_blog_zhongwenfanyi-2024.3.6.0.dist-info/top_level.txt
go_blog_zhongwenfanyi-2024.3.6.0.dist-info/RECORD
